phonic/__init__.py
phonic/_base.py
phonic/_types.py
phonic/client.py
phonic_python-0.1.17.dist-info/licenses/LICENSE
phonic_python-0.1.17.dist-info/METADATA
phonic_python-0.1.17.dist-info/WHEEL
phonic_python-0.1.17.dist-info/top_level.txt
phonic_python-0.1.17.dist-info/RECORD
