Metadata-Version: 2.4
Name: phonic-python
Version: 0.1.17
Summary: The official Python SDK for building voice AI with Phonic
Author-email: Phonic <support@phonic.co>
License: MIT
Project-URL: Homepage, https://phonic.co
Project-URL: Repository, https://github.com/Phonic-Co/phonic-python
Project-URL: Bug Tracker, https://github.com/Phonic-Co/phonic-python/issues
Requires-Python: >=3.11
License-File: LICENSE
Requires-Dist: fastapi>=0.109.0
Requires-Dist: loguru>=0.7.3
Requires-Dist: numpy<2.0.0,>=1.24.0
Requires-Dist: python-dotenv>=1.0.1
Requires-Dist: requests>=2.32.3
Requires-Dist: scipy>=1.15.1
Requires-Dist: sounddevice>=0.5.1
Requires-Dist: typing-extensions>=4.12.2
Requires-Dist: uvicorn>=0.27.0
Requires-Dist: websockets>=15.0.0
Provides-Extra: dev
Requires-Dist: ruff>=0.8.0; extra == "dev"
Requires-Dist: mypy>=1.13.0; extra == "dev"
Requires-Dist: pre-commit>=4.0.0; extra == "dev"
Requires-Dist: types-requests>=2.32.0; extra == "dev"
Dynamic: license-file
